py_vendor/__init__.py
py_vendor/__main__.py
py_vendor/console.py
py_vendor/run.py
py_vendor/shell.py
py_vendor-0.1.2.dist-info/entry_points.txt
py_vendor-0.1.2.dist-info/LICENSE
py_vendor-0.1.2.dist-info/WHEEL
py_vendor-0.1.2.dist-info/METADATA
py_vendor-0.1.2.dist-info/RECORD
